ipynbcompress/VERSION
ipynbcompress/__init__.py
ipynbcompress/ipynbcompress.py
ipynbcompress-0.5.0.data/scripts/ipynb-compress
ipynbcompress-0.5.0.dist-info/LICENSE
ipynbcompress-0.5.0.dist-info/METADATA
ipynbcompress-0.5.0.dist-info/WHEEL
ipynbcompress-0.5.0.dist-info/top_level.txt
ipynbcompress-0.5.0.dist-info/RECORD
