Metadata-Version: 2.1
Name: ipynbcompress
Version: 0.5.0
Summary: Compress images in IPython/Jupyter notebooks
Home-page: https://github.com/arve0/ipynbcompress
Author: Arve Seljebu
Author-email: arve.seljebu@gmail.com
License: MIT
Keywords: ipynbcompress
Classifier: Development Status :: 2 - Pre-Alpha
Classifier: Intended Audience :: Developers
Classifier: License :: OSI Approved :: MIT License
Classifier: Natural Language :: English
Classifier: Programming Language :: Python :: 3
Classifier: Programming Language :: Python :: 3.8
License-File: LICENSE
Requires-Dist: Pillow
Requires-Dist: jsonschema
Requires-Dist: ipython
Requires-Dist: click
Requires-Dist: hurry.filesize
